{"verses":[{"number":"1","entities":[{"label":"Mispá","spot":"Mispa","uri":"http://pt.wikipedia.org/wiki/Misp%C3%A1","image":null,"categories":["Lugares"],"confidence":0.8668}]},{"number":"2","entities":[{"label":"Betel","spot":"Betel","uri":"http://pt.wikipedia.org/wiki/Betel","image":"https://commons.wikimedia.org/wiki/Special:FilePath/El_sueño_de_Jacob,_by_José_de_Ribera,_from_Prado_in_Google_Earth.jpg","categories":["Cidades da Antiguidade","Cidades de Israel","Testemunhas de Jeová","Assentamentos israelenses","Bíblia"],"confidence":0.8384}]},{"number":"3","entities":[{"label":"Jesus","spot":"Senhor","uri":"http://pt.wikipedia.org/wiki/Jesus","image":"https://commons.wikimedia.org/wiki/Special:FilePath/Christ_Icon_Sinai_6th_century.jpg","categories":["Jesus","Judeus do Império Romano"],"confidence":0.6606},{"label":"Javé","spot":"Deus de Israel","uri":"http://pt.wikipedia.org/wiki/Jav%C3%A9","image":null,"categories":["Javé","Deidades da guerra","Deidades do céu e clima"],"confidence":0.7016}]},{"number":"4","entities":[]},{"number":"5","entities":[{"label":"Tribos de Israel","spot":"filhos de Israel","uri":"http://pt.wikipedia.org/wiki/Tribos_de_Israel","image":"https://commons.wikimedia.org/wiki/Special:FilePath/12_Tribes_of_Israel_Map-pt.svg","categories":["Antigo Testamento","Tanakh"],"confidence":0.7706},{"label":"Jesus","spot":"Senhor","uri":"http://pt.wikipedia.org/wiki/Jesus","image":"https://commons.wikimedia.org/wiki/Special:FilePath/Christ_Icon_Sinai_6th_century.jpg","categories":["Jesus","Judeus do Império Romano"],"confidence":0.6913},{"label":"Mispá","spot":"Mispa","uri":"http://pt.wikipedia.org/wiki/Misp%C3%A1","image":null,"categories":["Lugares"],"confidence":0.8948}]},{"number":"6","entities":[{"label":"Tribos de Israel","spot":"filhos de Israel","uri":"http://pt.wikipedia.org/wiki/Tribos_de_Israel","image":"https://commons.wikimedia.org/wiki/Special:FilePath/12_Tribes_of_Israel_Map-pt.svg","categories":["Antigo Testamento","Tanakh"],"confidence":0.7526},{"label":"Benjamim","spot":"Benjamim","uri":"http://pt.wikipedia.org/wiki/Benjamim","image":null,"categories":null,"confidence":0.7417}]},{"number":"7","entities":[{"label":"Jesus","spot":"Senhor","uri":"http://pt.wikipedia.org/wiki/Jesus","image":"https://commons.wikimedia.org/wiki/Special:FilePath/Christ_Icon_Sinai_6th_century.jpg","categories":["Jesus","Judeus do Império Romano"],"confidence":0.6666}]},{"number":"8","entities":[{"label":"Tribos de Israel","spot":"tribos de Israel","uri":"http://pt.wikipedia.org/wiki/Tribos_de_Israel","image":"https://commons.wikimedia.org/wiki/Special:FilePath/12_Tribes_of_Israel_Map-pt.svg","categories":["Antigo Testamento","Tanakh"],"confidence":0.8218},{"label":"Mispá","spot":"Mispa","uri":"http://pt.wikipedia.org/wiki/Misp%C3%A1","image":null,"categories":["Lugares"],"confidence":0.874},{"label":"Gileade","spot":"Gileade","uri":"http://pt.wikipedia.org/wiki/Gileade","image":"https://commons.wikimedia.org/wiki/Special:FilePath/Hills_of_Gilead.jpg","categories":["Lugares da Bíblia hebraica","Lugares da Torá","Lugares bíblicos","Geografia da Jordânia"],"confidence":0.7339}]},{"number":"9","entities":[{"label":"Gileade","spot":"Gileade","uri":"http://pt.wikipedia.org/wiki/Gileade","image":"https://commons.wikimedia.org/wiki/Special:FilePath/Hills_of_Gilead.jpg","categories":["Lugares da Bíblia hebraica","Lugares da Torá","Lugares bíblicos","Geografia da Jordânia"],"confidence":0.7177}]},{"number":"10","entities":[{"label":"Espada","spot":"espada","uri":"http://pt.wikipedia.org/wiki/Espada","image":"https://commons.wikimedia.org/wiki/Special:FilePath/Espadon-Morges.jpg","categories":["Espadas"],"confidence":0.6353},{"label":"Gileade","spot":"Gileade","uri":"http://pt.wikipedia.org/wiki/Gileade","image":"https://commons.wikimedia.org/wiki/Special:FilePath/Hills_of_Gilead.jpg","categories":["Lugares da Bíblia hebraica","Lugares da Torá","Lugares bíblicos","Geografia da Jordânia"],"confidence":0.7177}]},{"number":"11","entities":[]},{"number":"12","entities":[{"label":"Gileade","spot":"Gileade","uri":"http://pt.wikipedia.org/wiki/Gileade","image":"https://commons.wikimedia.org/wiki/Special:FilePath/Hills_of_Gilead.jpg","categories":["Lugares da Bíblia hebraica","Lugares da Torá","Lugares bíblicos","Geografia da Jordânia"],"confidence":0.7347},{"label":"Silo","spot":"Siló","uri":"http://pt.wikipedia.org/wiki/Silo","image":"https://commons.wikimedia.org/wiki/Special:FilePath/Port_Giles_silos.jpg","categories":["Agricultura"],"confidence":0.8369},{"label":"Canaã","spot":"Canaã","uri":"http://pt.wikipedia.org/wiki/Cana%C3%A3","image":"https://commons.wikimedia.org/wiki/Special:FilePath/Star_of_David.svg","categories":["Personagens do Antigo Testamento","Lugares bíblicos","Fenícia","Regiões históricas","Locais das Cartas de Amarna"],"confidence":0.8596}]},{"number":"13","entities":[{"label":"Benjamim","spot":"Benjamim","uri":"http://pt.wikipedia.org/wiki/Benjamim","image":null,"categories":null,"confidence":0.6452},{"label":"Rimom","spot":"Rimom","uri":"http://pt.wikipedia.org/wiki/Rimom","image":"https://commons.wikimedia.org/wiki/Special:FilePath/Ancient_Galilee.jpg","categories":["Frases e palavras em hebraico","Lugares da Bíblia hebraica"],"confidence":0.7768}]},{"number":"14","entities":[{"label":"Gileade","spot":"Gileade","uri":"http://pt.wikipedia.org/wiki/Gileade","image":"https://commons.wikimedia.org/wiki/Special:FilePath/Hills_of_Gilead.jpg","categories":["Lugares da Bíblia hebraica","Lugares da Torá","Lugares bíblicos","Geografia da Jordânia"],"confidence":0.7321}]},{"number":"15","entities":[{"label":"Tribo de Benjamim","spot":"Benjamim","uri":"http://pt.wikipedia.org/wiki/Tribo_de_Benjamim","image":"https://commons.wikimedia.org/wiki/Special:FilePath/Benjamin2.JPG","categories":["Tribos de Israel"],"confidence":0.6798},{"label":"Jesus","spot":"Senhor","uri":"http://pt.wikipedia.org/wiki/Jesus","image":"https://commons.wikimedia.org/wiki/Special:FilePath/Christ_Icon_Sinai_6th_century.jpg","categories":["Jesus","Judeus do Império Romano"],"confidence":0.6652},{"label":"Tribos de Israel","spot":"tribos de Israel","uri":"http://pt.wikipedia.org/wiki/Tribos_de_Israel","image":"https://commons.wikimedia.org/wiki/Special:FilePath/12_Tribes_of_Israel_Map-pt.svg","categories":["Antigo Testamento","Tanakh"],"confidence":0.8165}]},{"number":"16","entities":[]},{"number":"17","entities":[{"label":"Benjamim","spot":"Benjamim","uri":"http://pt.wikipedia.org/wiki/Benjamim","image":null,"categories":null,"confidence":0.7012},{"label":"Tribo","spot":"tribo","uri":"http://pt.wikipedia.org/wiki/Tribo","image":null,"categories":["Antropologia"],"confidence":0.7203}]},{"number":"18","entities":[{"label":"Tribos de Israel","spot":"filhos de Israel","uri":"http://pt.wikipedia.org/wiki/Tribos_de_Israel","image":"https://commons.wikimedia.org/wiki/Special:FilePath/12_Tribes_of_Israel_Map-pt.svg","categories":["Antigo Testamento","Tanakh"],"confidence":0.7097}]},{"number":"19","entities":[{"label":"Jesus","spot":"Senhor","uri":"http://pt.wikipedia.org/wiki/Jesus","image":"https://commons.wikimedia.org/wiki/Special:FilePath/Christ_Icon_Sinai_6th_century.jpg","categories":["Jesus","Judeus do Império Romano"],"confidence":0.6707},{"label":"Silo","spot":"Siló","uri":"http://pt.wikipedia.org/wiki/Silo","image":"https://commons.wikimedia.org/wiki/Special:FilePath/Port_Giles_silos.jpg","categories":["Agricultura"],"confidence":0.8473},{"label":"Betel","spot":"Betel","uri":"http://pt.wikipedia.org/wiki/Betel","image":"https://commons.wikimedia.org/wiki/Special:FilePath/El_sueño_de_Jacob,_by_José_de_Ribera,_from_Prado_in_Google_Earth.jpg","categories":["Cidades da Antiguidade","Cidades de Israel","Testemunhas de Jeová","Assentamentos israelenses","Bíblia"],"confidence":0.8522},{"label":"Siquém","spot":"Siquém","uri":"http://pt.wikipedia.org/wiki/Siqu%C3%A9m","image":null,"categories":["Cidades da Bíblia hebraica","Cidades da Antiguidade","Cidades de Israel","Assentamentos israelenses","Samaritanos"],"confidence":0.8796}]},{"number":"20","entities":[{"label":"Benjamim","spot":"Benjamim","uri":"http://pt.wikipedia.org/wiki/Benjamim","image":null,"categories":null,"confidence":0.6743}]},{"number":"21","entities":[{"label":"Silo","spot":"Siló","uri":"http://pt.wikipedia.org/wiki/Silo","image":"https://commons.wikimedia.org/wiki/Special:FilePath/Port_Giles_silos.jpg","categories":["Agricultura"],"confidence":0.8348}]},{"number":"22","entities":[{"label":"Guerra","spot":"guerra","uri":"http://pt.wikipedia.org/wiki/Guerra","image":"https://commons.wikimedia.org/wiki/Special:FilePath/Cyprian_War.jpg","categories":["Guerra","Palavras de origem gótica na língua portuguesa"],"confidence":0.6453},{"label":"Gileade","spot":"Gileade","uri":"http://pt.wikipedia.org/wiki/Gileade","image":"https://commons.wikimedia.org/wiki/Special:FilePath/Hills_of_Gilead.jpg","categories":["Lugares da Bíblia hebraica","Lugares da Torá","Lugares bíblicos","Geografia da Jordânia"],"confidence":0.7377}]},{"number":"23","entities":[{"label":"Tribo de Benjamim","spot":"Benjamim","uri":"http://pt.wikipedia.org/wiki/Tribo_de_Benjamim","image":"https://commons.wikimedia.org/wiki/Special:FilePath/Benjamin2.JPG","categories":["Tribos de Israel"],"confidence":0.6766}]},{"number":"24","entities":[{"label":"Tribos de Israel","spot":"filhos de Israel","uri":"http://pt.wikipedia.org/wiki/Tribos_de_Israel","image":"https://commons.wikimedia.org/wiki/Special:FilePath/12_Tribes_of_Israel_Map-pt.svg","categories":["Antigo Testamento","Tanakh"],"confidence":0.7098},{"label":"Tribo","spot":"tribo","uri":"http://pt.wikipedia.org/wiki/Tribo","image":null,"categories":["Antropologia"],"confidence":0.7554},{"label":"Família","spot":"família","uri":"http://pt.wikipedia.org/wiki/Fam%C3%ADlia","image":"https://commons.wikimedia.org/wiki/Special:FilePath/Francisco_de_Goya_y_Lucientes_053.jpg","categories":["Sociologia","Genealogia","Direito de família","Família"],"confidence":0.7764}]},{"number":"25","entities":[]}]}
