{"verses":[{"number":"1","entities":[{"label":"Abraão","spot":"Abraão","uri":"http://pt.wikipedia.org/wiki/Abra%C3%A3o","image":"https://commons.wikimedia.org/wiki/Special:FilePath/Abraham_and_the_Three_Angels.png","categories":["Personagens do Antigo Testamento","Personagens dos Livros Apócrifos","Livro do Gênesis","Pessoas citadas na Divina Comédia (Paraíso)","Lei sacrificial judaica"],"confidence":0.8558},{"label":"Negev","spot":"Neguebe","uri":"http://pt.wikipedia.org/wiki/Neguev","image":"https://commons.wikimedia.org/wiki/Special:FilePath/Ruins_in_Negev_desert_Israe.jpg","categories":["Desertos de Israel"],"confidence":0.8756},{"label":"Cades","spot":"Cades","uri":"http://pt.wikipedia.org/wiki/Cades","image":null,"categories":["Lugares bíblicos","Estações do Êxodo"],"confidence":0.7576}]},{"number":"2","entities":[{"label":"Abraão","spot":"Abraão","uri":"http://pt.wikipedia.org/wiki/Abra%C3%A3o","image":"https://commons.wikimedia.org/wiki/Special:FilePath/Abraham_and_the_Three_Angels.png","categories":["Personagens do Antigo Testamento","Personagens dos Livros Apócrifos","Livro do Gênesis","Pessoas citadas na Divina Comédia (Paraíso)","Lei sacrificial judaica"],"confidence":0.8558},{"label":"Sara","spot":"Sara","uri":"http://pt.wikipedia.org/wiki/Sara","image":"https://commons.wikimedia.org/wiki/Special:FilePath/Sarah_Abraham.jpg","categories":["Personagens do Antigo Testamento","Pessoas citadas na Divina Comédia (Paraíso)","Mulheres na Bíblia"],"confidence":0.6396},{"label":"Abimeleque","spot":"Abimeleque","uri":"http://pt.wikipedia.org/wiki/Abimeleque","image":null,"categories":["Personagens do Antigo Testamento","Personagens do Tanakh","Personagens bíblicos","Monarcas da Torá"],"confidence":0.8866},{"label":"Faraó","spot":"rei","uri":"http://pt.wikipedia.org/wiki/Fara%C3%B3","image":"https://commons.wikimedia.org/wiki/Special:FilePath/Pharaoh.svg","categories":["Faraós","Títulos de nobreza","Monarcas da Torá"],"confidence":0.6723}]},{"number":"3","entities":[{"label":"Deus","spot":"Deus","uri":"http://pt.wikipedia.org/wiki/Deus","image":"https://commons.wikimedia.org/wiki/Special:FilePath/Ac_burleygriffin.jpg","categories":["Deus (monoteísmo)","Conceitos religiosos"],"confidence":0.7591},{"label":"Abimeleque","spot":"Abimeleque","uri":"http://pt.wikipedia.org/wiki/Abimeleque","image":null,"categories":["Personagens do Antigo Testamento","Personagens do Tanakh","Personagens bíblicos","Monarcas da Torá"],"confidence":0.888}]},{"number":"4","entities":[{"label":"Abimeleque","spot":"Abimeleque","uri":"http://pt.wikipedia.org/wiki/Abimeleque","image":null,"categories":["Personagens do Antigo Testamento","Personagens do Tanakh","Personagens bíblicos","Monarcas da Torá"],"confidence":0.8609},{"label":"Deus","spot":"Senhor","uri":"http://pt.wikipedia.org/wiki/Deus","image":"https://commons.wikimedia.org/wiki/Special:FilePath/Ac_burleygriffin.jpg","categories":["Deus (monoteísmo)","Conceitos religiosos"],"confidence":0.6988}]},{"number":"5","entities":[]},{"number":"6","entities":[{"label":"Deus","spot":"Deus","uri":"http://pt.wikipedia.org/wiki/Deus","image":"https://commons.wikimedia.org/wiki/Special:FilePath/Ac_burleygriffin.jpg","categories":["Deus (monoteísmo)","Conceitos religiosos"],"confidence":0.7397},{"label":"Sonho","spot":"sonho","uri":"http://pt.wikipedia.org/wiki/Sonho","image":"https://commons.wikimedia.org/wiki/Special:FilePath/Pierre-Cécile_Puvis_de_Chavannes_003.jpg","categories":["Sono","Psicologia"],"confidence":0.6645}]},{"number":"7","entities":[{"label":"Profeta","spot":"profeta","uri":"http://pt.wikipedia.org/wiki/Profeta","image":"https://commons.wikimedia.org/wiki/Special:FilePath/Isaiah's_Lips_Anointed_with_Fire.jpg","categories":["Ministros de culto religioso","Artes divinatórias","Dons do Espírito Santo","Profecias"],"confidence":0.7697}]},{"number":"8","entities":[{"label":"Abimeleque","spot":"Abimeleque","uri":"http://pt.wikipedia.org/wiki/Abimeleque","image":null,"categories":["Personagens do Antigo Testamento","Personagens do Tanakh","Personagens bíblicos","Monarcas da Torá"],"confidence":0.872}]},{"number":"9","entities":[{"label":"Abimeleque","spot":"Abimeleque","uri":"http://pt.wikipedia.org/wiki/Abimeleque","image":null,"categories":["Personagens do Antigo Testamento","Personagens do Tanakh","Personagens bíblicos","Monarcas da Torá"],"confidence":0.8728},{"label":"Abraão","spot":"Abraão","uri":"http://pt.wikipedia.org/wiki/Abra%C3%A3o","image":"https://commons.wikimedia.org/wiki/Special:FilePath/Abraham_and_the_Three_Angels.png","categories":["Personagens do Antigo Testamento","Personagens dos Livros Apócrifos","Livro do Gênesis","Pessoas citadas na Divina Comédia (Paraíso)","Lei sacrificial judaica"],"confidence":0.813}]},{"number":"10","entities":[{"label":"Abimeleque","spot":"Abimeleque","uri":"http://pt.wikipedia.org/wiki/Abimeleque","image":null,"categories":["Personagens do Antigo Testamento","Personagens do Tanakh","Personagens bíblicos","Monarcas da Torá"],"confidence":0.8713},{"label":"Abraão","spot":"Abraão","uri":"http://pt.wikipedia.org/wiki/Abra%C3%A3o","image":"https://commons.wikimedia.org/wiki/Special:FilePath/Abraham_and_the_Three_Angels.png","categories":["Personagens do Antigo Testamento","Personagens dos Livros Apócrifos","Livro do Gênesis","Pessoas citadas na Divina Comédia (Paraíso)","Lei sacrificial judaica"],"confidence":0.8109}]},{"number":"11","entities":[{"label":"Abraão","spot":"Abraão","uri":"http://pt.wikipedia.org/wiki/Abra%C3%A3o","image":"https://commons.wikimedia.org/wiki/Special:FilePath/Abraham_and_the_Three_Angels.png","categories":["Personagens do Antigo Testamento","Personagens dos Livros Apócrifos","Livro do Gênesis","Pessoas citadas na Divina Comédia (Paraíso)","Lei sacrificial judaica"],"confidence":0.8126},{"label":"Deus","spot":"Deus","uri":"http://pt.wikipedia.org/wiki/Deus","image":"https://commons.wikimedia.org/wiki/Special:FilePath/Ac_burleygriffin.jpg","categories":["Deus (monoteísmo)","Conceitos religiosos"],"confidence":0.7441}]},{"number":"12","entities":[]},{"number":"13","entities":[{"label":"Deus","spot":"Deus","uri":"http://pt.wikipedia.org/wiki/Deus","image":"https://commons.wikimedia.org/wiki/Special:FilePath/Ac_burleygriffin.jpg","categories":["Deus (monoteísmo)","Conceitos religiosos"],"confidence":0.7448}]},{"number":"14","entities":[{"label":"Abimeleque","spot":"Abimeleque","uri":"http://pt.wikipedia.org/wiki/Abimeleque","image":null,"categories":["Personagens do Antigo Testamento","Personagens do Tanakh","Personagens bíblicos","Monarcas da Torá"],"confidence":0.8785},{"label":"Abraão","spot":"Abraão","uri":"http://pt.wikipedia.org/wiki/Abra%C3%A3o","image":"https://commons.wikimedia.org/wiki/Special:FilePath/Abraham_and_the_Three_Angels.png","categories":["Personagens do Antigo Testamento","Personagens dos Livros Apócrifos","Livro do Gênesis","Pessoas citadas na Divina Comédia (Paraíso)","Lei sacrificial judaica"],"confidence":0.8188}]},{"number":"15","entities":[{"label":"Abimeleque","spot":"Abimeleque","uri":"http://pt.wikipedia.org/wiki/Abimeleque","image":null,"categories":["Personagens do Antigo Testamento","Personagens do Tanakh","Personagens bíblicos","Monarcas da Torá"],"confidence":0.8749}]},{"number":"16","entities":[{"label":"Shekel","spot":"siclos de prata","uri":"http://pt.wikipedia.org/wiki/Shekel","image":"https://commons.wikimedia.org/wiki/Special:FilePath/Carthage_EL_shekel_2250013.jpg","categories":["Moedas de Israel","Unidades de massa","Numismática","Estrangeirismos","Unidades de medida obsoletas"],"confidence":0.7905}]},{"number":"17","entities":[{"label":"Abraão","spot":"Abraão","uri":"http://pt.wikipedia.org/wiki/Abra%C3%A3o","image":"https://commons.wikimedia.org/wiki/Special:FilePath/Abraham_and_the_Three_Angels.png","categories":["Personagens do Antigo Testamento","Personagens dos Livros Apócrifos","Livro do Gênesis","Pessoas citadas na Divina Comédia (Paraíso)","Lei sacrificial judaica"],"confidence":0.8353},{"label":"Deus","spot":"Deus","uri":"http://pt.wikipedia.org/wiki/Deus","image":"https://commons.wikimedia.org/wiki/Special:FilePath/Ac_burleygriffin.jpg","categories":["Deus (monoteísmo)","Conceitos religiosos"],"confidence":0.7282},{"label":"Abimeleque","spot":"Abimeleque","uri":"http://pt.wikipedia.org/wiki/Abimeleque","image":null,"categories":["Personagens do Antigo Testamento","Personagens do Tanakh","Personagens bíblicos","Monarcas da Torá"],"confidence":0.8677}]},{"number":"18","entities":[{"label":"Deus","spot":"Senhor","uri":"http://pt.wikipedia.org/wiki/Deus","image":"https://commons.wikimedia.org/wiki/Special:FilePath/Ac_burleygriffin.jpg","categories":["Deus (monoteísmo)","Conceitos religiosos"],"confidence":0.6715},{"label":"Abimeleque","spot":"Abimeleque","uri":"http://pt.wikipedia.org/wiki/Abimeleque","image":null,"categories":["Personagens do Antigo Testamento","Personagens do Tanakh","Personagens bíblicos","Monarcas da Torá"],"confidence":0.8749},{"label":"Abraão","spot":"Abraão","uri":"http://pt.wikipedia.org/wiki/Abra%C3%A3o","image":"https://commons.wikimedia.org/wiki/Special:FilePath/Abraham_and_the_Three_Angels.png","categories":["Personagens do Antigo Testamento","Personagens dos Livros Apócrifos","Livro do Gênesis","Pessoas citadas na Divina Comédia (Paraíso)","Lei sacrificial judaica"],"confidence":0.8323}]}]}
