{"verses":[{"number":"1","entities":[{"label":"Jesus","spot":"Senhor","uri":"http://pt.wikipedia.org/wiki/Jesus","image":"https://commons.wikimedia.org/wiki/Special:FilePath/Christ_Icon_Sinai_6th_century.jpg","categories":["Jesus","Judeus do Império Romano"],"confidence":0.671},{"label":"Moisés","spot":"Moisés","uri":"http://pt.wikipedia.org/wiki/Mois%C3%A9s","image":"https://commons.wikimedia.org/wiki/Special:FilePath/Moses041.jpg","categories":["Moisés"],"confidence":0.8157},{"label":"Chá","spot":"te","uri":"http://pt.wikipedia.org/wiki/Ch%C3%A1","image":"https://commons.wikimedia.org/wiki/Special:FilePath/Tea_Cup.jpg","categories":["Chá","Bebidas"],"confidence":0.6137},{"label":"Faraó","spot":"Faraó","uri":"http://pt.wikipedia.org/wiki/Fara%C3%B3","image":"https://commons.wikimedia.org/wiki/Special:FilePath/Pharaoh.svg","categories":["Faraós","Títulos de nobreza","Monarcas da Torá"],"confidence":0.866},{"label":"Deus","spot":"Deus","uri":"http://pt.wikipedia.org/wiki/Deus","image":"https://commons.wikimedia.org/wiki/Special:FilePath/Ac_burleygriffin.jpg","categories":["Deus (monoteísmo)","Conceitos religiosos"],"confidence":0.7417},{"label":"Hebreus","spot":"hebreus","uri":"http://pt.wikipedia.org/wiki/Hebreus","image":"https://commons.wikimedia.org/wiki/Special:FilePath/Ajrud.jpg","categories":["Povos semitas","Hebreus","História de Israel"],"confidence":0.7827}]},{"number":"2","entities":[]},{"number":"3","entities":[{"label":"Jesus","spot":"Senhor","uri":"http://pt.wikipedia.org/wiki/Jesus","image":"https://commons.wikimedia.org/wiki/Special:FilePath/Christ_Icon_Sinai_6th_century.jpg","categories":["Jesus","Judeus do Império Romano"],"confidence":0.6619},{"label":"Bovinos","spot":"rebanho","uri":"http://pt.wikipedia.org/wiki/Bovinos","image":"https://commons.wikimedia.org/wiki/Special:FilePath/Brahman_Baby.jpg","categories":["Bovinos"],"confidence":0.7076},{"label":"Cavalo","spot":"cavalos","uri":"http://pt.wikipedia.org/wiki/Cavalo","image":"https://commons.wikimedia.org/wiki/Special:FilePath/Biandintz_eta_zaldiak_-_modified2.jpg","categories":["Cavalos","Transporte de tração animal","Espécies descritas em 1758"],"confidence":0.7103},{"label":"Burro","spot":"jumentos","uri":"http://pt.wikipedia.org/wiki/Asno","image":"https://commons.wikimedia.org/wiki/Special:FilePath/Donkey-01.jpg","categories":["Equídeos","Espécies descritas em 1758"],"confidence":0.7283},{"label":"Camelo","spot":"camelos","uri":"http://pt.wikipedia.org/wiki/Camelo","image":"https://commons.wikimedia.org/wiki/Special:FilePath/LA2-NSRW-1-0370.jpg","categories":["Camelídeos"],"confidence":0.7299},{"label":"Vaca","spot":"gado","uri":"http://pt.wikipedia.org/wiki/Bos_taurus","image":"https://commons.wikimedia.org/wiki/Special:FilePath/Vaca2.JPG","categories":["Bovinos","Animais domésticos","Mamíferos descritos em 1758"],"confidence":0.7838}]},{"number":"4","entities":[{"label":"Jesus","spot":"Senhor","uri":"http://pt.wikipedia.org/wiki/Jesus","image":"https://commons.wikimedia.org/wiki/Special:FilePath/Christ_Icon_Sinai_6th_century.jpg","categories":["Jesus","Judeus do Império Romano"],"confidence":0.6535},{"label":"Bovinos","spot":"rebanho","uri":"http://pt.wikipedia.org/wiki/Bovinos","image":"https://commons.wikimedia.org/wiki/Special:FilePath/Brahman_Baby.jpg","categories":["Bovinos"],"confidence":0.7175},{"label":"Antigo Egito","spot":"Egito","uri":"http://pt.wikipedia.org/wiki/Antigo_Egito","image":"https://commons.wikimedia.org/wiki/Special:FilePath/All_Gizah_Pyramids.jpg","categories":["Antigo Egito"],"confidence":0.8688},{"label":"Tribos de Israel","spot":"filhos de Israel","uri":"http://pt.wikipedia.org/wiki/Tribos_de_Israel","image":"https://commons.wikimedia.org/wiki/Special:FilePath/12_Tribes_of_Israel_Map-pt.svg","categories":["Antigo Testamento","Tanakh"],"confidence":0.7118}]},{"number":"5","entities":[{"label":"Jesus","spot":"Senhor","uri":"http://pt.wikipedia.org/wiki/Jesus","image":"https://commons.wikimedia.org/wiki/Special:FilePath/Christ_Icon_Sinai_6th_century.jpg","categories":["Jesus","Judeus do Império Romano"],"confidence":0.6404}]},{"number":"6","entities":[{"label":"Jesus","spot":"Senhor","uri":"http://pt.wikipedia.org/wiki/Jesus","image":"https://commons.wikimedia.org/wiki/Special:FilePath/Christ_Icon_Sinai_6th_century.jpg","categories":["Jesus","Judeus do Império Romano"],"confidence":0.6338},{"label":"Antigo Egito","spot":"egípcios","uri":"http://pt.wikipedia.org/wiki/Antigo_Egito","image":"https://commons.wikimedia.org/wiki/Special:FilePath/All_Gizah_Pyramids.jpg","categories":["Antigo Egito"],"confidence":0.7645}]},{"number":"7","entities":[{"label":"Faraó","spot":"Faraó","uri":"http://pt.wikipedia.org/wiki/Fara%C3%B3","image":"https://commons.wikimedia.org/wiki/Special:FilePath/Pharaoh.svg","categories":["Faraós","Títulos de nobreza","Monarcas da Torá"],"confidence":0.8774}]},{"number":"8","entities":[{"label":"Jesus","spot":"Senhor","uri":"http://pt.wikipedia.org/wiki/Jesus","image":"https://commons.wikimedia.org/wiki/Special:FilePath/Christ_Icon_Sinai_6th_century.jpg","categories":["Jesus","Judeus do Império Romano"],"confidence":0.6777},{"label":"Moisés","spot":"Moisés","uri":"http://pt.wikipedia.org/wiki/Mois%C3%A9s","image":"https://commons.wikimedia.org/wiki/Special:FilePath/Moses041.jpg","categories":["Moisés"],"confidence":0.8361},{"label":"Aarão","spot":"Arão","uri":"http://pt.wikipedia.org/wiki/Aar%C3%A3o","image":"https://commons.wikimedia.org/wiki/Special:FilePath/148_-_aarao_irmao_mais_velho_de_moises.jpg","categories":["Sumos Sacerdotes de Israel","Livro de Êxodo","Torá","História e cronologia da Bíblia","Sumo sacerdote de Israel","Personagens do Antigo Testamento","Moisés"],"confidence":0.7725},{"label":"Enchente","spot":"cheias","uri":"http://pt.wikipedia.org/wiki/Inunda%C3%A7%C3%A3o","image":"https://commons.wikimedia.org/wiki/Special:FilePath/Alicante(30-09-1997).JPG","categories":["Enchentes","Riscos naturais","Hidrologia","Hidrologia ambiental","Urbanismo"],"confidence":0.6735},{"label":"Cinza","spot":"cinza","uri":"http://pt.wikipedia.org/wiki/Cinza","image":"https://commons.wikimedia.org/wiki/Special:FilePath/Color_icon_gray.svg","categories":["Cores"],"confidence":0.725},{"label":"Forno","spot":"forno","uri":"http://pt.wikipedia.org/wiki/Forno","image":"https://commons.wikimedia.org/wiki/Special:FilePath/Jean-François_Millet_(II)_005.jpg","categories":["Fornos","Eletrodomésticos","Utensílios culinários"],"confidence":0.753},{"label":"Faraó","spot":"Faraó","uri":"http://pt.wikipedia.org/wiki/Fara%C3%B3","image":"https://commons.wikimedia.org/wiki/Special:FilePath/Pharaoh.svg","categories":["Faraós","Títulos de nobreza","Monarcas da Torá"],"confidence":0.8614}]},{"number":"9","entities":[{"label":"Poeira","spot":"pó","uri":"http://pt.wikipedia.org/wiki/Poeira","image":"https://commons.wikimedia.org/wiki/Special:FilePath/Dust-storm-Texas-1935.png","categories":["Saúde","Limpeza","Meteorologia","Poluição atmosférica"],"confidence":0.6732},{"label":"Antigo Egito","spot":"Egito","uri":"http://pt.wikipedia.org/wiki/Antigo_Egito","image":"https://commons.wikimedia.org/wiki/Special:FilePath/All_Gizah_Pyramids.jpg","categories":["Antigo Egito"],"confidence":0.8624}]},{"number":"10","entities":[{"label":"Cinza","spot":"cinza","uri":"http://pt.wikipedia.org/wiki/Cinza","image":"https://commons.wikimedia.org/wiki/Special:FilePath/Color_icon_gray.svg","categories":["Cores"],"confidence":0.6912},{"label":"Forno","spot":"forno","uri":"http://pt.wikipedia.org/wiki/Forno","image":"https://commons.wikimedia.org/wiki/Special:FilePath/Jean-François_Millet_(II)_005.jpg","categories":["Fornos","Eletrodomésticos","Utensílios culinários"],"confidence":0.7325},{"label":"Faraó","spot":"Faraó","uri":"http://pt.wikipedia.org/wiki/Fara%C3%B3","image":"https://commons.wikimedia.org/wiki/Special:FilePath/Pharaoh.svg","categories":["Faraós","Títulos de nobreza","Monarcas da Torá"],"confidence":0.8556},{"label":"Moisés","spot":"Moisés","uri":"http://pt.wikipedia.org/wiki/Mois%C3%A9s","image":"https://commons.wikimedia.org/wiki/Special:FilePath/Moses041.jpg","categories":["Moisés"],"confidence":0.806}]},{"number":"11","entities":[{"label":"Moisés","spot":"Moisés","uri":"http://pt.wikipedia.org/wiki/Mois%C3%A9s","image":"https://commons.wikimedia.org/wiki/Special:FilePath/Moses041.jpg","categories":["Moisés"],"confidence":0.8146},{"label":"Antigo Egito","spot":"egípcios","uri":"http://pt.wikipedia.org/wiki/Antigo_Egito","image":"https://commons.wikimedia.org/wiki/Special:FilePath/All_Gizah_Pyramids.jpg","categories":["Antigo Egito"],"confidence":0.7399}]},{"number":"12","entities":[{"label":"Faraó","spot":"Faraó","uri":"http://pt.wikipedia.org/wiki/Fara%C3%B3","image":"https://commons.wikimedia.org/wiki/Special:FilePath/Pharaoh.svg","categories":["Faraós","Títulos de nobreza","Monarcas da Torá"],"confidence":0.8662},{"label":"Jesus","spot":"Senhor","uri":"http://pt.wikipedia.org/wiki/Jesus","image":"https://commons.wikimedia.org/wiki/Special:FilePath/Christ_Icon_Sinai_6th_century.jpg","categories":["Jesus","Judeus do Império Romano"],"confidence":0.6572},{"label":"Moisés","spot":"Moisés","uri":"http://pt.wikipedia.org/wiki/Mois%C3%A9s","image":"https://commons.wikimedia.org/wiki/Special:FilePath/Moses041.jpg","categories":["Moisés"],"confidence":0.8222}]},{"number":"13","entities":[{"label":"Jesus","spot":"Senhor","uri":"http://pt.wikipedia.org/wiki/Jesus","image":"https://commons.wikimedia.org/wiki/Special:FilePath/Christ_Icon_Sinai_6th_century.jpg","categories":["Jesus","Judeus do Império Romano"],"confidence":0.672},{"label":"Moisés","spot":"Moisés","uri":"http://pt.wikipedia.org/wiki/Mois%C3%A9s","image":"https://commons.wikimedia.org/wiki/Special:FilePath/Moses041.jpg","categories":["Moisés"],"confidence":0.824},{"label":"Faraó","spot":"Faraó","uri":"http://pt.wikipedia.org/wiki/Fara%C3%B3","image":"https://commons.wikimedia.org/wiki/Special:FilePath/Pharaoh.svg","categories":["Faraós","Títulos de nobreza","Monarcas da Torá"],"confidence":0.8612},{"label":"Deus","spot":"Deus","uri":"http://pt.wikipedia.org/wiki/Deus","image":"https://commons.wikimedia.org/wiki/Special:FilePath/Ac_burleygriffin.jpg","categories":["Deus (monoteísmo)","Conceitos religiosos"],"confidence":0.7264},{"label":"Hebreus","spot":"hebreus","uri":"http://pt.wikipedia.org/wiki/Hebreus","image":"https://commons.wikimedia.org/wiki/Special:FilePath/Ajrud.jpg","categories":["Povos semitas","Hebreus","História de Israel"],"confidence":0.791}]},{"number":"14","entities":[]},{"number":"15","entities":[]},{"number":"16","entities":[]},{"number":"17","entities":[]},{"number":"18","entities":[{"label":"Rocha","spot":"pedras","uri":"http://pt.wikipedia.org/wiki/Rocha","image":"https://commons.wikimedia.org/wiki/Special:FilePath/DirkvdM_rocks.jpg","categories":["Rochas"],"confidence":0.6751},{"label":"Egito","spot":"Egito","uri":"http://pt.wikipedia.org/wiki/Egito","image":"https://commons.wikimedia.org/wiki/Special:FilePath/Flag_of_Egypt.svg","categories":["Egito"],"confidence":0.8484}]},{"number":"19","entities":[{"label":"Gado","spot":"gado","uri":"http://pt.wikipedia.org/wiki/Gado","image":null,"categories":["Pecuária"],"confidence":0.7376},{"label":"Rocha","spot":"pedras","uri":"http://pt.wikipedia.org/wiki/Rocha","image":"https://commons.wikimedia.org/wiki/Special:FilePath/DirkvdM_rocks.jpg","categories":["Rochas"],"confidence":0.6957}]},{"number":"20","entities":[{"label":"Faraó","spot":"Faraó","uri":"http://pt.wikipedia.org/wiki/Fara%C3%B3","image":"https://commons.wikimedia.org/wiki/Special:FilePath/Pharaoh.svg","categories":["Faraós","Títulos de nobreza","Monarcas da Torá"],"confidence":0.8579},{"label":"Palavra","spot":"palavra","uri":"http://pt.wikipedia.org/wiki/Palavra","image":null,"categories":["Lexicologia"],"confidence":0.6744},{"label":"Gado","spot":"gado","uri":"http://pt.wikipedia.org/wiki/Gado","image":null,"categories":["Pecuária"],"confidence":0.7546}]},{"number":"21","entities":[{"label":"Palavra","spot":"palavra","uri":"http://pt.wikipedia.org/wiki/Palavra","image":null,"categories":["Lexicologia"],"confidence":0.6719},{"label":"Jesus","spot":"Senhor","uri":"http://pt.wikipedia.org/wiki/Jesus","image":"https://commons.wikimedia.org/wiki/Special:FilePath/Christ_Icon_Sinai_6th_century.jpg","categories":["Jesus","Judeus do Império Romano"],"confidence":0.6573},{"label":"Gado","spot":"gado","uri":"http://pt.wikipedia.org/wiki/Gado","image":null,"categories":["Pecuária"],"confidence":0.7659}]},{"number":"22","entities":[{"label":"Jesus","spot":"Senhor","uri":"http://pt.wikipedia.org/wiki/Jesus","image":"https://commons.wikimedia.org/wiki/Special:FilePath/Christ_Icon_Sinai_6th_century.jpg","categories":["Jesus","Judeus do Império Romano"],"confidence":0.6725},{"label":"Moisés","spot":"Moisés","uri":"http://pt.wikipedia.org/wiki/Mois%C3%A9s","image":"https://commons.wikimedia.org/wiki/Special:FilePath/Moses041.jpg","categories":["Moisés"],"confidence":0.8056},{"label":"Rocha","spot":"pedras","uri":"http://pt.wikipedia.org/wiki/Rocha","image":"https://commons.wikimedia.org/wiki/Special:FilePath/DirkvdM_rocks.jpg","categories":["Rochas"],"confidence":0.7145},{"label":"Antigo Egito","spot":"Egito","uri":"http://pt.wikipedia.org/wiki/Antigo_Egito","image":"https://commons.wikimedia.org/wiki/Special:FilePath/All_Gizah_Pyramids.jpg","categories":["Antigo Egito"],"confidence":0.8655},{"label":"Planta","spot":"planta","uri":"http://pt.wikipedia.org/wiki/Planta_%28geometria_descritiva%29","image":"https://commons.wikimedia.org/wiki/Special:FilePath/DallasMunicipalCenterPlan1946.jpg","categories":["Geometria descritiva","Engenharia cartográfica","Geomática","Infografia"],"confidence":0.6976}]},{"number":"23","entities":[{"label":"Moisés","spot":"Moisés","uri":"http://pt.wikipedia.org/wiki/Mois%C3%A9s","image":"https://commons.wikimedia.org/wiki/Special:FilePath/Moses041.jpg","categories":["Moisés"],"confidence":0.8115},{"label":"Bordão","spot":"bordão","uri":"http://pt.wikipedia.org/wiki/Bord%C3%A3o","image":null,"categories":["Expressões","Linguística","Teoria musical","Cultura popular"],"confidence":0.6482},{"label":"Deus","spot":"Senhor","uri":"http://pt.wikipedia.org/wiki/Deus","image":"https://commons.wikimedia.org/wiki/Special:FilePath/Ac_burleygriffin.jpg","categories":["Deus (monoteísmo)","Conceitos religiosos"],"confidence":0.6849},{"label":"Trovão","spot":"trovões","uri":"http://pt.wikipedia.org/wiki/Trov%C3%A3o","image":"https://commons.wikimedia.org/wiki/Special:FilePath/Lightning_14.07.2009_20-42-33.JPG","categories":["Fenômenos atmosféricos","Meteorologia"],"confidence":0.7482},{"label":"Rocha","spot":"pedras","uri":"http://pt.wikipedia.org/wiki/Rocha","image":"https://commons.wikimedia.org/wiki/Special:FilePath/DirkvdM_rocks.jpg","categories":["Rochas"],"confidence":0.7173},{"label":"Egito","spot":"Egito","uri":"http://pt.wikipedia.org/wiki/Egito","image":"https://commons.wikimedia.org/wiki/Special:FilePath/Flag_of_Egypt.svg","categories":["Egito"],"confidence":0.8607}]},{"number":"24","entities":[{"label":"Rocha","spot":"pedras","uri":"http://pt.wikipedia.org/wiki/Rocha","image":"https://commons.wikimedia.org/wiki/Special:FilePath/DirkvdM_rocks.jpg","categories":["Rochas"],"confidence":0.6948},{"label":"Egito","spot":"Egito","uri":"http://pt.wikipedia.org/wiki/Egito","image":"https://commons.wikimedia.org/wiki/Special:FilePath/Flag_of_Egypt.svg","categories":["Egito"],"confidence":0.8534},{"label":"Nação","spot":"nação","uri":"http://pt.wikipedia.org/wiki/Na%C3%A7%C3%A3o","image":null,"categories":["Nacionalidade","Conceitos filosóficos","Ciência política","Etnicidade","Geografia política","Nacionalismo"],"confidence":0.6623}]},{"number":"25","entities":[{"label":"Egito","spot":"Egito","uri":"http://pt.wikipedia.org/wiki/Egito","image":"https://commons.wikimedia.org/wiki/Special:FilePath/Flag_of_Egypt.svg","categories":["Egito"],"confidence":0.8491},{"label":"Rocha","spot":"pedras","uri":"http://pt.wikipedia.org/wiki/Rocha","image":"https://commons.wikimedia.org/wiki/Special:FilePath/DirkvdM_rocks.jpg","categories":["Rochas"],"confidence":0.6777},{"label":"Planta","spot":"planta","uri":"http://pt.wikipedia.org/wiki/Planta_%28geometria_descritiva%29","image":"https://commons.wikimedia.org/wiki/Special:FilePath/DallasMunicipalCenterPlan1946.jpg","categories":["Geometria descritiva","Engenharia cartográfica","Geomática","Infografia"],"confidence":0.6725},{"label":"Pradaria","spot":"campo","uri":"http://pt.wikipedia.org/wiki/Pradaria","image":"https://commons.wikimedia.org/wiki/Special:FilePath/Konza1.jpg","categories":["Biomas terrestres"],"confidence":0.6271}]},{"number":"26","entities":[{"label":"Terra de Gósen","spot":"terra de Gósen","uri":"http://pt.wikipedia.org/wiki/Terra_de_G%C3%B3sen","image":null,"categories":["Lugares da Torá","Antigo Egito","Rio Nilo"],"confidence":0.8983},{"label":"Tribos de Israel","spot":"filhos de Israel","uri":"http://pt.wikipedia.org/wiki/Tribos_de_Israel","image":"https://commons.wikimedia.org/wiki/Special:FilePath/12_Tribes_of_Israel_Map-pt.svg","categories":["Antigo Testamento","Tanakh"],"confidence":0.7689},{"label":"Rocha","spot":"pedras","uri":"http://pt.wikipedia.org/wiki/Rocha","image":"https://commons.wikimedia.org/wiki/Special:FilePath/DirkvdM_rocks.jpg","categories":["Rochas"],"confidence":0.6974}]},{"number":"27","entities":[{"label":"Faraó","spot":"Faraó","uri":"http://pt.wikipedia.org/wiki/Fara%C3%B3","image":"https://commons.wikimedia.org/wiki/Special:FilePath/Pharaoh.svg","categories":["Faraós","Títulos de nobreza","Monarcas da Torá"],"confidence":0.885},{"label":"Moisés","spot":"Moisés","uri":"http://pt.wikipedia.org/wiki/Mois%C3%A9s","image":"https://commons.wikimedia.org/wiki/Special:FilePath/Moses041.jpg","categories":["Moisés"],"confidence":0.8467},{"label":"Aarão","spot":"Arão","uri":"http://pt.wikipedia.org/wiki/Aar%C3%A3o","image":"https://commons.wikimedia.org/wiki/Special:FilePath/148_-_aarao_irmao_mais_velho_de_moises.jpg","categories":["Sumos Sacerdotes de Israel","Livro de Êxodo","Torá","História e cronologia da Bíblia","Sumo sacerdote de Israel","Personagens do Antigo Testamento","Moisés"],"confidence":0.8144},{"label":"Jesus","spot":"Senhor","uri":"http://pt.wikipedia.org/wiki/Jesus","image":"https://commons.wikimedia.org/wiki/Special:FilePath/Christ_Icon_Sinai_6th_century.jpg","categories":["Jesus","Judeus do Império Romano"],"confidence":0.7279}]},{"number":"28","entities":[{"label":"Jesus","spot":"Senhor","uri":"http://pt.wikipedia.org/wiki/Jesus","image":"https://commons.wikimedia.org/wiki/Special:FilePath/Christ_Icon_Sinai_6th_century.jpg","categories":["Jesus","Judeus do Império Romano"],"confidence":0.7058},{"label":"Trovão","spot":"trovões","uri":"http://pt.wikipedia.org/wiki/Trov%C3%A3o","image":"https://commons.wikimedia.org/wiki/Special:FilePath/Lightning_14.07.2009_20-42-33.JPG","categories":["Fenômenos atmosféricos","Meteorologia"],"confidence":0.7214},{"label":"Rocha","spot":"pedras","uri":"http://pt.wikipedia.org/wiki/Rocha","image":"https://commons.wikimedia.org/wiki/Special:FilePath/DirkvdM_rocks.jpg","categories":["Rochas"],"confidence":0.6779}]},{"number":"29","entities":[{"label":"Moisés","spot":"Moisés","uri":"http://pt.wikipedia.org/wiki/Mois%C3%A9s","image":"https://commons.wikimedia.org/wiki/Special:FilePath/Moses041.jpg","categories":["Moisés"],"confidence":0.8131},{"label":"Trovão","spot":"trovões","uri":"http://pt.wikipedia.org/wiki/Trov%C3%A3o","image":"https://commons.wikimedia.org/wiki/Special:FilePath/Lightning_14.07.2009_20-42-33.JPG","categories":["Fenômenos atmosféricos","Meteorologia"],"confidence":0.6986},{"label":"Rocha","spot":"pedras","uri":"http://pt.wikipedia.org/wiki/Rocha","image":"https://commons.wikimedia.org/wiki/Special:FilePath/DirkvdM_rocks.jpg","categories":["Rochas"],"confidence":0.6507}]},{"number":"30","entities":[{"label":"Deus","spot":"Deus","uri":"http://pt.wikipedia.org/wiki/Deus","image":"https://commons.wikimedia.org/wiki/Special:FilePath/Ac_burleygriffin.jpg","categories":["Deus (monoteísmo)","Conceitos religiosos"],"confidence":0.7069}]},{"number":"31","entities":[{"label":"Linho","spot":"linho","uri":"http://pt.wikipedia.org/wiki/Linho","image":"https://commons.wikimedia.org/wiki/Special:FilePath/Linum_usitatissimum_-_Köhler–s_Medizinal-Pflanzen-088.jpg","categories":["Linaceae","Tecidos naturais"],"confidence":0.8027},{"label":"Cevada","spot":"cevada","uri":"http://pt.wikipedia.org/wiki/Cevada","image":"https://commons.wikimedia.org/wiki/Special:FilePath/Barley.jpg","categories":["Cereais","Poaceae","Hordeum","Flora de Portugal"],"confidence":0.8638},{"label":"Espiga","spot":"espiga","uri":"http://pt.wikipedia.org/wiki/Espiga","image":"https://commons.wikimedia.org/wiki/Special:FilePath/Getreide.jpg","categories":["Morfologia vegetal"],"confidence":0.772},{"label":"Flor","spot":"flor","uri":"http://pt.wikipedia.org/wiki/Flor","image":"https://commons.wikimedia.org/wiki/Special:FilePath/Bluete-Schema.svg","categories":["Flores","Anatomia vegetal"],"confidence":0.7718}]},{"number":"32","entities":[{"label":"Trigo","spot":"trigo","uri":"http://pt.wikipedia.org/wiki/Trigo","image":"https://commons.wikimedia.org/wiki/Special:FilePath/Wheat_field.jpg","categories":["Cereais","Trigo","Poaceae"],"confidence":0.825},{"label":"Centeio","spot":"centeio","uri":"http://pt.wikipedia.org/wiki/Centeio","image":"https://commons.wikimedia.org/wiki/Special:FilePath/Rogge_aar_Secale_cereale_(4×3).jpg","categories":["Flora de Portugal","Secale","Cereais"],"confidence":0.8324}]},{"number":"33","entities":[{"label":"Moisés","spot":"Moisés","uri":"http://pt.wikipedia.org/wiki/Mois%C3%A9s","image":"https://commons.wikimedia.org/wiki/Special:FilePath/Moses041.jpg","categories":["Moisés"],"confidence":0.8058},{"label":"Faraó","spot":"Faraó","uri":"http://pt.wikipedia.org/wiki/Fara%C3%B3","image":"https://commons.wikimedia.org/wiki/Special:FilePath/Pharaoh.svg","categories":["Faraós","Títulos de nobreza","Monarcas da Torá"],"confidence":0.8565},{"label":"Trovão","spot":"trovões","uri":"http://pt.wikipedia.org/wiki/Trov%C3%A3o","image":"https://commons.wikimedia.org/wiki/Special:FilePath/Lightning_14.07.2009_20-42-33.JPG","categories":["Fenômenos atmosféricos","Meteorologia"],"confidence":0.706},{"label":"Rocha","spot":"pedras","uri":"http://pt.wikipedia.org/wiki/Rocha","image":"https://commons.wikimedia.org/wiki/Special:FilePath/DirkvdM_rocks.jpg","categories":["Rochas"],"confidence":0.6536}]},{"number":"34","entities":[{"label":"Faraó","spot":"Faraó","uri":"http://pt.wikipedia.org/wiki/Fara%C3%B3","image":"https://commons.wikimedia.org/wiki/Special:FilePath/Pharaoh.svg","categories":["Faraós","Títulos de nobreza","Monarcas da Torá"],"confidence":0.858},{"label":"Rocha","spot":"pedras","uri":"http://pt.wikipedia.org/wiki/Rocha","image":"https://commons.wikimedia.org/wiki/Special:FilePath/DirkvdM_rocks.jpg","categories":["Rochas"],"confidence":0.6871},{"label":"Trovão","spot":"trovões","uri":"http://pt.wikipedia.org/wiki/Trov%C3%A3o","image":"https://commons.wikimedia.org/wiki/Special:FilePath/Lightning_14.07.2009_20-42-33.JPG","categories":["Fenômenos atmosféricos","Meteorologia"],"confidence":0.727}]},{"number":"35","entities":[{"label":"Faraó","spot":"Faraó","uri":"http://pt.wikipedia.org/wiki/Fara%C3%B3","image":"https://commons.wikimedia.org/wiki/Special:FilePath/Pharaoh.svg","categories":["Faraós","Títulos de nobreza","Monarcas da Torá"],"confidence":0.8723},{"label":"Tribos de Israel","spot":"filhos de Israel","uri":"http://pt.wikipedia.org/wiki/Tribos_de_Israel","image":"https://commons.wikimedia.org/wiki/Special:FilePath/12_Tribes_of_Israel_Map-pt.svg","categories":["Antigo Testamento","Tanakh"],"confidence":0.7519},{"label":"Jesus","spot":"Senhor","uri":"http://pt.wikipedia.org/wiki/Jesus","image":"https://commons.wikimedia.org/wiki/Special:FilePath/Christ_Icon_Sinai_6th_century.jpg","categories":["Jesus","Judeus do Império Romano"],"confidence":0.7005},{"label":"Moisés","spot":"Moisés","uri":"http://pt.wikipedia.org/wiki/Mois%C3%A9s","image":"https://commons.wikimedia.org/wiki/Special:FilePath/Moses041.jpg","categories":["Moisés"],"confidence":0.8346}]}]}
