{"verses":[{"number":"1","entities":[]},{"number":"2","entities":[]},{"number":"3","entities":[]},{"number":"4","entities":[{"label":"Egito","spot":"Egito","uri":"http://pt.wikipedia.org/wiki/Egito","image":"https://commons.wikimedia.org/wiki/Special:FilePath/Flag_of_Egypt.svg","categories":["Egito"],"confidence":0.8613},{"label":"Moisés","spot":"Moisés","uri":"http://pt.wikipedia.org/wiki/Mois%C3%A9s","image":"https://commons.wikimedia.org/wiki/Special:FilePath/Moses041.jpg","categories":["Moisés"],"confidence":0.8138},{"label":"Aarão","spot":"Arão","uri":"http://pt.wikipedia.org/wiki/Aar%C3%A3o","image":"https://commons.wikimedia.org/wiki/Special:FilePath/148_-_aarao_irmao_mais_velho_de_moises.jpg","categories":["Sumos Sacerdotes de Israel","Livro de Êxodo","Torá","História e cronologia da Bíblia","Sumo sacerdote de Israel","Personagens do Antigo Testamento","Moisés"],"confidence":0.7811},{"label":"Miriã","spot":"Miriã","uri":"http://pt.wikipedia.org/wiki/Miri%C3%A3","image":"https://commons.wikimedia.org/wiki/Special:FilePath/Miriams_Tanz.jpg","categories":["Personagens do Antigo Testamento","Livro de Êxodo","Mulheres na Bíblia"],"confidence":0.894}]},{"number":"5","entities":[{"label":"Balaque","spot":"Balaque","uri":"http://pt.wikipedia.org/wiki/Balaque","image":null,"categories":["Monarcas da Torá","Personagens do Antigo Testamento","Reis de Moabe"],"confidence":0.8688},{"label":"Moabe","spot":"Moabe","uri":"http://pt.wikipedia.org/wiki/Moabe","image":null,"categories":["Lugares bíblicos"],"confidence":0.8852},{"label":"Balaão","spot":"Balaão","uri":"http://pt.wikipedia.org/wiki/Bala%C3%A3o","image":"https://commons.wikimedia.org/wiki/Special:FilePath/Gustav_Jaeger_Bileam_Engel.jpg","categories":["Profetas","Personagens do Antigo Testamento","Moisés"],"confidence":0.89},{"label":"Bëor","spot":"Beor","uri":"http://pt.wikipedia.org/wiki/B%C3%ABor","image":null,"categories":["Personagens de O Silmarillion","Edains da Terra Média"],"confidence":0.7287},{"label":"Abel-Sitim","spot":"Sitim","uri":"http://pt.wikipedia.org/wiki/Abila_%28Pereia%29","image":null,"categories":null,"confidence":0.7801},{"label":"Gilgal","spot":"Gilgal","uri":"http://pt.wikipedia.org/wiki/Gilgal","image":null,"categories":["Tanakh"],"confidence":0.8276},{"label":"Jesus","spot":"Senhor","uri":"http://pt.wikipedia.org/wiki/Jesus","image":"https://commons.wikimedia.org/wiki/Special:FilePath/Christ_Icon_Sinai_6th_century.jpg","categories":["Jesus","Judeus do Império Romano"],"confidence":0.6218}]},{"number":"6","entities":[{"label":"Jesus","spot":"Senhor","uri":"http://pt.wikipedia.org/wiki/Jesus","image":"https://commons.wikimedia.org/wiki/Special:FilePath/Christ_Icon_Sinai_6th_century.jpg","categories":["Jesus","Judeus do Império Romano"],"confidence":0.6039},{"label":"Deus","spot":"Deus","uri":"http://pt.wikipedia.org/wiki/Deus","image":"https://commons.wikimedia.org/wiki/Special:FilePath/Ac_burleygriffin.jpg","categories":["Deus (monoteísmo)","Conceitos religiosos"],"confidence":0.7082},{"label":"Bezerros","spot":"bezerros","uri":"http://pt.wikipedia.org/wiki/Bezerros","image":"https://commons.wikimedia.org/wiki/Special:FilePath/BrasaoBezerrosPE.jpg","categories":["Bezerros"],"confidence":0.7692}]},{"number":"7","entities":[{"label":"Azeite","spot":"azeite","uri":"http://pt.wikipedia.org/wiki/Azeite","image":"https://commons.wikimedia.org/wiki/Special:FilePath/Olive-tree-fruit-august-0.jpg","categories":["Óleos vegetais","Culinária de Portugal","Culinária do Mediterrâneo"],"confidence":0.778},{"label":"Fruto","spot":"fruto","uri":"http://pt.wikipedia.org/wiki/Fruto","image":"https://commons.wikimedia.org/wiki/Special:FilePath/Camellia_sinensis-fruto.jpg","categories":["Frutos","Anatomia vegetal"],"confidence":0.7047}]},{"number":"8","entities":[{"label":"Jesus","spot":"Senhor","uri":"http://pt.wikipedia.org/wiki/Jesus","image":"https://commons.wikimedia.org/wiki/Special:FilePath/Christ_Icon_Sinai_6th_century.jpg","categories":["Jesus","Judeus do Império Romano"],"confidence":0.649},{"label":"Andes","spot":"andes","uri":"http://pt.wikipedia.org/wiki/Cordilheira_dos_Andes","image":"https://commons.wikimedia.org/wiki/Special:FilePath/Aerial_photo_of_the_Andes.jpg","categories":["Andes"],"confidence":0.7824},{"label":"Deus","spot":"Deus","uri":"http://pt.wikipedia.org/wiki/Deus","image":"https://commons.wikimedia.org/wiki/Special:FilePath/Ac_burleygriffin.jpg","categories":["Deus (monoteísmo)","Conceitos religiosos"],"confidence":0.7254}]},{"number":"9","entities":[{"label":"Deus","spot":"Senhor","uri":"http://pt.wikipedia.org/wiki/Deus","image":"https://commons.wikimedia.org/wiki/Special:FilePath/Ac_burleygriffin.jpg","categories":["Deus (monoteísmo)","Conceitos religiosos"],"confidence":0.662},{"label":"Sabedoria","spot":"sabedoria","uri":"http://pt.wikipedia.org/wiki/Sabedoria","image":"https://commons.wikimedia.org/wiki/Special:FilePath/Efez_Celsus_Library_3_RB.jpg","categories":["Filosofia","Educação"],"confidence":0.6387}]},{"number":"10","entities":[{"label":"Efá","spot":"efa","uri":"http://pt.wikipedia.org/wiki/Ef%C3%A1","image":null,"categories":["Cidades da Antiguidade","Personagens do Antigo Testamento","Personagens bíblicos","Personagens do Tanakh","Unidades de volume"],"confidence":0.6647}]},{"number":"11","entities":[]},{"number":"12","entities":[]},{"number":"13","entities":[]},{"number":"14","entities":[]},{"number":"15","entities":[{"label":"Azeitona","spot":"azeitona","uri":"http://pt.wikipedia.org/wiki/Azeitona","image":"https://commons.wikimedia.org/wiki/Special:FilePath/Olive-tree-fruit-august-0.jpg","categories":["Culinária de Portugal","Árvores","Frutos","Culinária do Mediterrâneo","Oleaceae"],"confidence":0.8765},{"label":"Azeite","spot":"azeite","uri":"http://pt.wikipedia.org/wiki/Azeite","image":"https://commons.wikimedia.org/wiki/Special:FilePath/Olive-tree-fruit-august-0.jpg","categories":["Óleos vegetais","Culinária de Portugal","Culinária do Mediterrâneo"],"confidence":0.8033},{"label":"Vindima","spot":"vindima","uri":"http://pt.wikipedia.org/wiki/Vindima","image":"https://commons.wikimedia.org/wiki/Special:FilePath/Grape_gathering.jpg","categories":["Enologia"],"confidence":0.8379},{"label":"Vinho","spot":"vinho","uri":"http://pt.wikipedia.org/wiki/Vinho","image":"https://commons.wikimedia.org/wiki/Special:FilePath/Schwappender_Wein.jpg","categories":["Bebidas","Vinhos"],"confidence":0.7818}]},{"number":"16","entities":[{"label":"Omri","spot":"Onri","uri":"http://pt.wikipedia.org/wiki/Omri","image":null,"categories":["Reis de Israel","Personagens do Antigo Testamento"],"confidence":0.8349}]}]}
